Workbook

Sheet Dashboard
B2: 🍜 BETALBATIM RESTAURANT — VISUAL DASHBOARD
B3: Plan numbers pull from the 12-Month P&L Plan tab. Actual numbers pull from the Daily Sales Log tab as you fill it in.
B5: PLANNED (12-MONTH)
B6: Planned Annual Revenue | D6: Planned Annual Op. Profit | F6: Avg Gross Margin | H6: Break-even Covers/day | J6: Lowest Monthly Cash
B7: =SUM('Monthly P&L Plan'!B9:M9) | D7: =SUM('Monthly P&L Plan'!B17:M17) | F7: =AVERAGE('Monthly P&L Plan'!B13:M13) | H7: =Assumptions!$C$23 | J7: =MIN('Monthly P&L Plan'!B18:M18)
B10: ACTUAL SO FAR (from Daily Sales Log)
B11: Revenue Logged | D11: Covers Logged | F11: Avg Check (Actual) | H11: Avg Food Cost % (Actual) | J11: Campaigns Logged
B12: =SUM('Daily Sales Log'!F2:F401) | D12: =SUM('Daily Sales Log'!E2:E401) | F12: =IFERROR(SUM('Daily Sales Log'!F2:F401)/SUM('Daily Sales Log'!E2:E401),0) | H12: =IFERROR(SUM('Daily Sales Log'!G2:G401)/SUM('Daily Sales Log'!F2:F401),0) | J12: =COUNTA('Campaign Tracker'!A2:A61)-1
B15: WHERE EACH ₹100 OF REVENUE GOES (avg/month, plan)
B16: Food Cost | C16: =AVERAGE('Monthly P&L Plan'!B11:M11)
B17: Core Fixed Costs | C17: =AVERAGE('Monthly P&L Plan'!B14:M14)
B18: Marketing | C18: =AVERAGE('Monthly P&L Plan'!B15:M15)
B19: Operating Profit | C19: =AVERAGE('Monthly P&L Plan'!B17:M17)
B110: Tabs: Assumptions (edit inputs) → Monthly P&L Plan (12-month scenario) → Daily Sales Log (log real days) → Menu Performance → Campaign Tracker

Sheet Assumptions
A1: 🍜 BETALBATIM RESTAURANT — ASSUMPTIONS & SETUP
A2: Change the yellow cells only. Every other sheet in this workbook calculates from these numbers.
A4: CAPACITY & PRICING
B5: Seats | C5: 20 | D5: How many diners you can seat at once (18-24 fits a compact, boutique format).
B6: Average Spend Per Person — ASP (₹) | C6: 550 | D6: ₹ per guest. Betalbatim comparables run ₹400-750/person for pan-Asian, mid-range dining.
B7: Target Food Cost % | C7: 0.32 | D7: Ingredients should be ~28-35% of revenue. Above 40% usually means under-pricing or waste.
B8: Operating Days per Month | C8: 26 | D8: Days you're actually open. Betalbatim stays open ~year-round, unlike Agonda's monsoon shutdowns.
A10: MONTHLY CORE FIXED COSTS (rent, salaries, utilities — everything you pay whether you sell 5 covers or 50)
B11: Rent (₹/month) | C11: 60000 | D11: Ground-floor 18-24 seat premises on a quiet Betalbatim/Majorda lane.
B12: Staff Salaries (₹/month) | C12: 45000 | D12: 1 chef + 1 kitchen helper. FOH run by owner/spouse to avoid a 3rd salary.
B13: Utilities (₹/month) | C13: 12000 | D13: Electricity, gas, water, internet.
B14: Misc / Repairs (₹/month) | C14: 5000 | D14: Linen, cleaning supplies, small breakages.
B15: Total Core Fixed Costs (₹/month) | C15: =SUM(C11:C14)
A17: STARTUP CAPITAL & CASH
B18: Total Capex Budget (₹) | C18: 1000000 | D18: Your hard ceiling: deposit, interiors, kitchen equipment, licences.
B19: Starting Working Capital / Cash (₹) | C19: 250000 | D19: What's left after capex — this is your survival cushion for slow months.
A21: BREAK-EVEN (auto-calculated — the two numbers to check before signing any lease)
B22: Break-even Revenue (₹/month) | C22: =Assumptions!$C$15/(1-Assumptions!$C$7) | D22: Fixed Costs ÷ (1 − Food Cost%). Minimum revenue needed just to not lose money.
B23: Break-even Covers/day | C23: =Assumptions!$C$22/(Assumptions!$C$6*Assumptions!$C$8) | D23: Revenue ÷ (ASP × operating days). If you can't realistically hit this many covers/day, the location doesn't work.

Sheet Monthly P&L Plan
A1: 📆 12-MONTH P&L PLAN (Apr–Mar) — edit Covers/day per month, everything else calculates
A2: This is your planning scenario. Once you're open, compare it against the Daily Sales Log tab and adjust Covers/day to match reality.
A4: Month | B4: Apr | C4: May | D4: Jun | E4: Jul | F4: Aug | G4: Sep | H4: Oct | I4: Nov | J4: Dec | K4: Jan | L4: Feb | M4: Mar
A5: Season | B5: Shoulder | C5: Shoulder | D5: Monsoon | E5: Monsoon | F5: Monsoon | G5: Monsoon | H5: Shoulder | I5: Peak | J5: Peak | K5: Peak | L5: Peak | M5: Shoulder
A6: Operating Days | B6: 26 | C6: 26 | D6: 22 | E6: 22 | F6: 22 | G6: 24 | H6: 26 | I6: 27 | J6: 27 | K6: 27 | L6: 26 | M6: 26
A7: Covers/day (editable) | B7: 45 | C7: 42 | D7: 34 | E7: 33 | F7: 33 | G7: 36 | H7: 44 | I7: 56 | J7: 63 | K7: 60 | L7: 57 | M7: 48
A8: ASP (₹) | B8: =Assumptions!$C$6 | C8: =Assumptions!$C$6 | D8: =Assumptions!$C$6 | E8: =Assumptions!$C$6 | F8: =Assumptions!$C$6 | G8: =Assumptions!$C$6 | H8: =Assumptions!$C$6 | I8: =Assumptions!$C$6 | ... M8: =Assumptions!$C$6
A9: Revenue (₹) | B9: =B6*B7*B8 | C9: =C6*C7*C8 | D9: =D6*D7*D8 | E9: =E6*E7*E8 | F9: =F6*F7*F8 | G9: =G6*G7*G8 | H9: =H6*H7*H8 | I9: =I6*I7*I8 | ... M9: =M6*M7*M8
A10: Food Cost % | B10: =Assumptions!$C$7 | C10: =Assumptions!$C$7 | D10: =Assumptions!$C$7 | E10: =Assumptions!$C$7 | F10: =Assumptions!$C$7 | G10: =Assumptions!$C$7 | H10: =Assumptions!$C$7 | I10: =Assumptions!$C$7 | ... M10: =Assumptions!$C$7
A11: Food Cost (₹) | B11: =B9*B10 | C11: =C9*C10 | D11: =D9*D10 | E11: =E9*E10 | F11: =F9*F10 | G11: =G9*G10 | H11: =H9*H10 | I11: =I9*I10 | ... M11: =M9*M10
A12: Gross Profit (₹) | B12: =B9-B11 | C12: =C9-C11 | D12: =D9-D11 | E12: =E9-E11 | F12: =F9-F11 | G12: =G9-G11 | H12: =H9-H11 | I12: =I9-I11 | ... M12: =M9-M11
A13: Gross Margin % | B13: =IF(B9=0,0,B12/B9) | C13: =IF(C9=0,0,C12/C9) | D13: =IF(D9=0,0,D12/D9) | E13: =IF(E9=0,0,E12/E9) | F13: =IF(F9=0,0,F12/F9) | G13: =IF(G9=0,0,G12/G9) | H13: =IF(H9=0,0,H12/H9) | I13: =IF(I9=0,0,I12/I9) | ... M13: =IF(M9=0,0,M12/M9)
A14: Core Fixed Costs (₹) | B14: =Assumptions!$C$15 | C14: =Assumptions!$C$15 | D14: =Assumptions!$C$15 | E14: =Assumptions!$C$15 | F14: =Assumptions!$C$15 | G14: =Assumptions!$C$15 | H14: =Assumptions!$C$15 | I14: =Assumptions!$C$15 | ... M14: =Assumptions!$C$15
A15: Marketing Spend (₹) | B15: 15000 | C15: 15000 | D15: 6000 | E15: 5000 | F15: 5000 | G15: 6000 | H15: 8000 | I15: 12000 | J15: 15000 | K15: 12000 | L15: 10000 | M15: 8000
A16: Total Costs (₹) | B16: =B14+B15 | C16: =C14+C15 | D16: =D14+D15 | E16: =E14+E15 | F16: =F14+F15 | G16: =G14+G15 | H16: =H14+H15 | I16: =I14+I15 | ... M16: =M14+M15
A17: Operating Profit (₹) | B17: =B12-B16 | C17: =C12-C16 | D17: =D12-D16 | E17: =E12-E16 | F17: =F12-F16 | G17: =G12-G16 | H17: =H12-H16 | I17: =I12-I16 | ... M17: =M12-M16
A18: Cumulative Cash (₹) | B18: =Assumptions!$C$19+B17 | C18: =B18+C17 | D18: =C18+D17 | E18: =D18+E17 | F18: =E18+F17 | G18: =F18+G17 | H18: =G18+H17 | I18: =H18+I17 | J18: =I18+J17 | ... M18: =L18+M17
A19: Break-even Covers/day | B19: =IF(B10=1,0,(B16/(1-B10))/(B8*B6)) | C19: =IF(C10=1,0,(C16/(1-C10))/(C8*C6)) | D19: =IF(D10=1,0,(D16/(1-D10))/(D8*D6)) | E19: =IF(E10=1,0,(E16/(1-E10))/(E8*E6)) | F19: =IF(F10=1,0,(F16/(1-F10))/(F8*F6)) | G19: =IF(G10=1,0,(G16/(1-G10))/(G8*G6)) | H19: =IF(H10=1,0,(H16/(1-H10))/(H8*H6)) | I19: =IF(I10=1,0,(I16/(1-I10))/(I8*I6)) | ... M19: =IF(M10=1,0,(M16/(1-M10))/(M8*M6))
A20: vs. Break-even | B20: =IF(B7>=B19,"✅ Above","⚠️ Below") | C20: =IF(C7>=C19,"✅ Above","⚠️ Below") | D20: =IF(D7>=D19,"✅ Above","⚠️ Below") | E20: =IF(E7>=E19,"✅ Above","⚠️ Below") | F20: =IF(F7>=F19,"✅ Above","⚠️ Below") | G20: =IF(G7>=G19,"✅ Above","⚠️ Below") | H20: =IF(H7>=H19,"✅ Above","⚠️ Below") | I20: =IF(I7>=I19,"✅ Above","⚠️ Below") | ... M20: =IF(M7>=M19,"✅ Above","⚠️ Below")

Sheet Daily Sales Log
A1: Date | B1: Day | C1: Lunch Covers | D1: Dinner Covers | E1: Total Covers | F1: Revenue (₹) | G1: Food Cost (₹) | H1: Food Cost % | I1: Avg Check (₹) | J1: Offer Active | K1: Offer Cost (₹) | L1: Notes
B2: =IF(A2="","",TEXT(A2,"ddd")) | E2: =IF(AND(C2="",D2=""),"",C2+D2) | H2: =IF(OR(F2="",F2=0),"",G2/F2) | I2: =IF(OR(E2="",E2=0),"",F2/E2)
B3: =IF(A3="","",TEXT(A3,"ddd")) | E3: =IF(AND(C3="",D3=""),"",C3+D3) | H3: =IF(OR(F3="",F3=0),"",G3/F3) | I3: =IF(OR(E3="",E3=0),"",F3/E3)
B4: =IF(A4="","",TEXT(A4,"ddd")) | E4: =IF(AND(C4="",D4=""),"",C4+D4) | H4: =IF(OR(F4="",F4=0),"",G4/F4) | I4: =IF(OR(E4="",E4=0),"",F4/E4)
B5: =IF(A5="","",TEXT(A5,"ddd")) | E5: =IF(AND(C5="",D5=""),"",C5+D5) | H5: =IF(OR(F5="",F5=0),"",G5/F5) | I5: =IF(OR(E5="",E5=0),"",F5/E5)
B6: =IF(A6="","",TEXT(A6,"ddd")) | E6: =IF(AND(C6="",D6=""),"",C6+D6) | H6: =IF(OR(F6="",F6=0),"",G6/F6) | I6: =IF(OR(E6="",E6=0),"",F6/E6)
B7: =IF(A7="","",TEXT(A7,"ddd")) | E7: =IF(AND(C7="",D7=""),"",C7+D7) | H7: =IF(OR(F7="",F7=0),"",G7/F7) | I7: =IF(OR(E7="",E7=0),"",F7/E7)
B8: =IF(A8="","",TEXT(A8,"ddd")) | E8: =IF(AND(C8="",D8=""),"",C8+D8) | H8: =IF(OR(F8="",F8=0),"",G8/F8) | I8: =IF(OR(E8="",E8=0),"",F8/E8)
B9: =IF(A9="","",TEXT(A9,"ddd")) | E9: =IF(AND(C9="",D9=""),"",C9+D9) | H9: =IF(OR(F9="",F9=0),"",G9/F9) | I9: =IF(OR(E9="",E9=0),"",F9/E9)
B10: =IF(A10="","",TEXT(A10,"ddd")) | E10: =IF(AND(C10="",D10=""),"",C10+D10) | H10: =IF(OR(F10="",F10=0),"",G10/F10) | I10: =IF(OR(E10="",E10=0),"",F10/E10)
B11: =IF(A11="","",TEXT(A11,"ddd")) | E11: =IF(AND(C11="",D11=""),"",C11+D11) | H11: =IF(OR(F11="",F11=0),"",G11/F11) | I11: =IF(OR(E11="",E11=0),"",F11/E11)
B12: =IF(A12="","",TEXT(A12,"ddd")) | E12: =IF(AND(C12="",D12=""),"",C12+D12) | H12: =IF(OR(F12="",F12=0),"",G12/F12) | I12: =IF(OR(E12="",E12=0),"",F12/E12)
B13: =IF(A13="","",TEXT(A13,"ddd")) | E13: =IF(AND(C13="",D13=""),"",C13+D13) | H13: =IF(OR(F13="",F13=0),"",G13/F13) | I13: =IF(OR(E13="",E13=0),"",F13/E13)
... B401: =IF(A401="","",TEXT(A401,"ddd")) | E401: =IF(AND(C401="",D401=""),"",C401+D401) | H401: =IF(OR(F401="",F401=0),"",G401/F401) | I401: =IF(OR(E401="",E401=0),"",F401/E401)

Sheet Menu Performance
A1: Item | B1: Category | C1: Selling Price (₹) | D1: Food Cost (₹) | E1: Qty Sold | F1: Revenue (₹) | G1: Gross Margin %
A2: Steamed Chicken Momos (8pc) | B2: Momos | C2: 220 | D2: 71 | F2: =IF(OR(C2="",E2=""),"",C2*E2) | G2: =IF(OR(C2="",C2=0),"",(C2-D2)/C2)
A3: Steamed Veg Momos (8pc) | B3: Momos | C3: 180 | D3: 50 | F3: =IF(OR(C3="",E3=""),"",C3*E3) | G3: =IF(OR(C3="",C3=0),"",(C3-D3)/C3)
A4: Pan-fried Chicken Momos (8pc) | B4: Momos | C4: 240 | D4: 80 | F4: =IF(OR(C4="",E4=""),"",C4*E4) | G4: =IF(OR(C4="",C4=0),"",(C4-D4)/C4)
A5: Chicken Thukpa | B5: Soup | C5: 210 | D5: 65 | F5: =IF(OR(C5="",E5=""),"",C5*E5) | G5: =IF(OR(C5="",C5=0),"",(C5-D5)/C5)
A6: Veg Thukpa | B6: Soup | C6: 180 | D6: 48 | F6: =IF(OR(C6="",E6=""),"",C6*E6) | G6: =IF(OR(C6="",C6=0),"",(C6-D6)/C6)
A7: Veg Manchow Soup | B7: Soup | C7: 160 | D7: 42 | F7: =IF(OR(C7="",E7=""),"",C7*E7) | G7: =IF(OR(C7="",C7=0),"",(C7-D7)/C7)
A8: Chicken Hot & Sour Soup | B8: Soup | C8: 180 | D8: 52 | F8: =IF(OR(C8="",E8=""),"",C8*E8) | G8: =IF(OR(C8="",C8=0),"",(C8-D8)/C8)
A9: Hakka Noodles (Chicken) | B9: Noodles | C9: 240 | D9: 72 | F9: =IF(OR(C9="",E9=""),"",C9*E9) | G9: =IF(OR(C9="",C9=0),"",(C9-D9)/C9)
A10: Hakka Noodles (Veg) | B10: Noodles | C10: 200 | D10: 52 | F10: =IF(OR(C10="",E10=""),"",C10*E10) | G10: =IF(OR(C10="",C10=0),"",(C10-D10)/C10)
A11: Schezwan Noodles (Chicken) | B11: Noodles | C11: 250 | D11: 78 | F11: =IF(OR(C11="",E11=""),"",C11*E11) | G11: =IF(OR(C11="",C11=0),"",(C11-D11)/C11)
A12: Chilli Chicken (Dry) | B12: Rice | C12: 280 | D12: 98 | F12: =IF(OR(C12="",E12=""),"",C12*E12) | G12: =IF(OR(C12="",C12=0),"",(C12-D12)/C12)
A13: Chilli Paneer | B13: Rice | C13: 250 | D13: 80 | F13: =IF(OR(C13="",E13=""),"",C13*E13) | G13: =IF(OR(C13="",C13=0),"",(C13-D13)/C13)
... A21: Fresh Lime Soda | B21: Beverages | C21: 100 | D21: 12 | F21: =IF(OR(C21="",E21=""),"",C21*E21) | G21: =IF(OR(C21="",C21=0),"",(C21-D21)/C21)
F22: =IF(OR(C22="",E22=""),"",C22*E22) | G22: =IF(OR(C22="",C22=0),"",(C22-D22)/C22)
F23: =IF(OR(C23="",E23=""),"",C23*E23) | G23: =IF(OR(C23="",C23=0),"",(C23-D23)/C23)
F24: =IF(OR(C24="",E24=""),"",C24*E24) | G24: =IF(OR(C24="",C24=0),"",(C24-D24)/C24)
F25: =IF(OR(C25="",E25=""),"",C25*E25) | G25: =IF(OR(C25="",C25=0),"",(C25-D25)/C25)
F26: =IF(OR(C26="",E26=""),"",C26*E26) | G26: =IF(OR(C26="",C26=0),"",(C26-D26)/C26)
F27: =IF(OR(C27="",E27=""),"",C27*E27) | G27: =IF(OR(C27="",C27=0),"",(C27-D27)/C27)
F28: =IF(OR(C28="",E28=""),"",C28*E28) | G28: =IF(OR(C28="",C28=0),"",(C28-D28)/C28)
F29: =IF(OR(C29="",E29=""),"",C29*E29) | G29: =IF(OR(C29="",C29=0),"",(C29-D29)/C29)
F30: =IF(OR(C30="",E30=""),"",C30*E30) | G30: =IF(OR(C30="",C30=0),"",(C30-D30)/C30)
F31: =IF(OR(C31="",E31=""),"",C31*E31) | G31: =IF(OR(C31="",C31=0),"",(C31-D31)/C31)
F32: =IF(OR(C32="",E32=""),"",C32*E32) | G32: =IF(OR(C32="",C32=0),"",(C32-D32)/C32)
F33: =IF(OR(C33="",E33=""),"",C33*E33) | G33: =IF(OR(C33="",C33=0),"",(C33-D33)/C33)
... F61: =IF(OR(C61="",E61=""),"",C61*E61) | G61: =IF(OR(C61="",C61=0),"",(C61-D61)/C61)

Sheet Campaign Tracker
A1: Campaign Name | B1: Type | C1: Start Date | D1: End Date | E1: Spend (₹) | F1: Free Meals Cost (₹) | G1: Total Cost (₹) | H1: Promo Code | I1: Reach | J1: Inquiries | K1: Conversions | L1: Revenue Attributed (₹) | M1: ROAS
A2: Example: Pre-opening Tasting | B2: Influencer | G2: =IF(AND(E2="",F2=""),"",E2+F2) | H2: TASTE10 | M2: =IF(OR(G2="",G2=0),"",L2/G2)
G3: =IF(AND(E3="",F3=""),"",E3+F3) | M3: =IF(OR(G3="",G3=0),"",L3/G3)
G4: =IF(AND(E4="",F4=""),"",E4+F4) | M4: =IF(OR(G4="",G4=0),"",L4/G4)
G5: =IF(AND(E5="",F5=""),"",E5+F5) | M5: =IF(OR(G5="",G5=0),"",L5/G5)
G6: =IF(AND(E6="",F6=""),"",E6+F6) | M6: =IF(OR(G6="",G6=0),"",L6/G6)
G7: =IF(AND(E7="",F7=""),"",E7+F7) | M7: =IF(OR(G7="",G7=0),"",L7/G7)
G8: =IF(AND(E8="",F8=""),"",E8+F8) | M8: =IF(OR(G8="",G8=0),"",L8/G8)
G9: =IF(AND(E9="",F9=""),"",E9+F9) | M9: =IF(OR(G9="",G9=0),"",L9/G9)
G10: =IF(AND(E10="",F10=""),"",E10+F10) | M10: =IF(OR(G10="",G10=0),"",L10/G10)
G11: =IF(AND(E11="",F11=""),"",E11+F11) | M11: =IF(OR(G11="",G11=0),"",L11/G11)
G12: =IF(AND(E12="",F12=""),"",E12+F12) | M12: =IF(OR(G12="",G12=0),"",L12/G12)
G13: =IF(AND(E13="",F13=""),"",E13+F13) | M13: =IF(OR(G13="",G13=0),"",L13/G13)
G14: =IF(AND(E14="",F14=""),"",E14+F14) | M14: =IF(OR(G14="",G14=0),"",L14/G14)
... G61: =IF(AND(E61="",F61=""),"",E61+F61) | M61: =IF(OR(G61="",G61=0),"",L61/G61)
