Workbook

Sheet Start Here
A1: Restaurant Economics Calculator
A2: Betalbatim 24-seat Chinese-Tibetan-Korean kitchen
A4: How to use
A5: 1. Edit only the blue cells on 'Inputs' | B5: Yellow-filled blue cells are inputs. Black cells are formulas. Green cells pull from another sheet.
A6: 2. Read the results | B6: BreakEven: sales needed to cover costs. Seasons: 12-month profit. Setup: startup budget and payback. Menu: dish-level pricing check.
A7: 3. Replace my estimates | B7: Wages, deposit, interior costs, utilities and ingredient costs are estimates, not quotes. Replace them with real quotes before deciding.
A9: Key terms
A10: Covers | B10: Number of guests served.
A11: ASP | B11: Average spend per head, before GST.
A12: Food cost % | B12: Ingredient cost divided by sales. Aim for a blended 28-31%.
A13: Contribution margin | B13: Share of each rupee of sales left after variable costs. Break-even sales = fixed costs / contribution margin.
A14: Prime cost | B14: Food cost plus staff cost as a share of sales. Aim for 60-65% or lower.
A16: Not included
A17: Owner's pay | B17: Set to 0 on Inputs. If you work front-of-house unpaid, enter a drawing there to see the true profit.
A18: Income tax and GST | B18: Menu prices are treated as before GST. 5% GST is collected from guests and is not your income. Income tax is not modelled.
A19: Repairs and replacement | B19: Only a small allowance is in 'Repairs, licences, software, marketing'. Equipment will need replacing over time.
A20: Delivery apps | B20: Not modelled. Aggregators take about 20-25% commission, which would cut the contribution margin sharply.

Sheet Inputs
A1: Inputs
A2: Edit the blue cells. Everything else recalculates.
A4: SALES
A5: Average spend per head, ASP (₹, before GST) | B5: 550 | C5: From your plan: planning range ₹400-700.
A6: Seats | B6: 28 | C6: 28 covers from the current plan (18 inside + 10 in the garden); flex to about 30 in peak.
A7: Days open per month | B7: 30 | C7: Reduce if you close one day a week.
A8: What-if covers per day | B8: 20 | C8: Used on BreakEven to test a single scenario.
A9: Items ordered per guest | B9: 2.3 | C9: Estimate; used on Menu to check the implied ASP.
A10: FIXED COSTS (₹ per month)
A11: Rent | B11: 40000 | C11: Your figure.
A12: Chef | B12: 25000 | C12: Estimate: Chinese/Tibetan wok-trained, also cooks the Korean items.
A13: Kitchen helper | B13: 13000 | C13: Estimate.
A14: Server / cashier | B14: 12000 | C14: Estimate: third staff member.
A15: Electricity, gas, water, internet | B15: 13000 | C15: Estimate. A wok-heavy kitchen uses a lot of gas; track it in month one.
A16: Repairs, licences, software, marketing | B16: 8000 | C16: Estimate.
A17: Owner's drawing (optional) | B17: 0 | C17: Enter a salary for yourself to see profit after paying yourself.
A18: Total fixed costs per month | B18: =SUM(B11:B17)
A20: VARIABLE COSTS (% of sales)
A21: Food cost % | B21: 0.3 | C21: Blended target 28-31% from your plan. The Menu sheet shows what your dishes actually imply.
A22: Waste allowance (on ingredient cost) | B22: 0.08 | C22: Spillage, over-portioning, staff meals. Typical range 4-8%. Used on Menu.
A23: Card/UPI fees and packaging % | B23: 0.02 | C23: Estimate.
A24: Total variable cost % | B24: =B21+B23
A25: Contribution margin | B25: =1-B24
A27: SEASONS
A28: Season | B28: Covers per day | C28: Note
A29: Peak | B29: 25 | C29: Nov-Mar. Illustrative: assumes a good season.
A30: Shoulder | B30: 15 | C30: Apr-May, Sep-Oct.
A31: Monsoon | B31: 8 | C31: Jun-Aug. Many Goa beach places shut; you won't, but footfall drops.
A32: Safety haircut on annual profit | B32: 0.33 | C32: First-year plans are usually optimistic. Seasons shows profit before and after this haircut.
A34: SETUP COSTS (one-time)
A35: Rent deposit (months of rent) | B35: 3 | C35: Typical Goa lease: 3-6 months. Negotiate it.
A36: Rent deposit amount | B36: =B35*B11
A37: Interiors, furniture, lighting (28 seats) | B37: 300000 | C37: Estimate. Get 2-3 quotes.
A38: Kitchen equipment (wok burner, steamers, fryer, fridge) | B38: 220000 | C38: Estimate. Buying second-hand can cut this.
A39: Licences, FSSAI, trade licence, signage | B39: 40000 | C39: Estimate.
A40: POS, menu printing, launch marketing | B40: 60000 | C40: Estimate.
A41: Crockery, cutlery, opening stock | B41: 80000 | C41: Estimate.
A42: Cash reserve (months of fixed costs) | B42: 3 | C42: Cushion for the monsoon months. Do not skip it.
A43: Your total budget (₹) | B43: 1050000 | C43: From your plan: about ₹10.5 lakh, flexible to ₹11-12 lakh.

Sheet BreakEven
A1: Break-even and what-if
A2: All values calculate from Inputs.
A3: BREAK-EVEN
A4: Fixed costs per month | B4: =Inputs!B18
A5: Contribution margin | B5: =Inputs!B25
A6: Break-even sales per month | B6: =IFERROR(B4/B5,0)
A7: Break-even sales per day | B7: =IFERROR(B6/Inputs!B7,0)
A8: Break-even covers per day | B8: =IFERROR(B7/Inputs!B5,0)
A9: Seat turns per day at break-even | B9: =IFERROR(B8/Inputs!B6,0)
A10: Rent as % of sales at break-even | B10: =IFERROR(Inputs!B11/B6,0) | C10: Rent above about 15% of sales is a warning sign.
A12: WHAT-IF (covers per day from Inputs)
A13: Covers per day | B13: =Inputs!B8
A14: Monthly sales | B14: =B13*Inputs!B7*Inputs!B5
A15: Food cost | B15: =B14*Inputs!B21
A16: Card fees and packaging | B16: =B14*Inputs!B23
A17: Fixed costs | B17: =B4
A18: Monthly profit (before tax) | B18: =B14-B15-B16-B17
A19: Net margin | B19: =IFERROR(B18/B14,0)
A20: Prime cost % (food + staff) | B20: =IFERROR((B15+Inputs!B12+Inputs!B13+Inputs!B14)/B14,0) | C20: Aim for 60-65% or lower.
A21: Rent % of sales | B21: =IFERROR(Inputs!B11/B14,0)
A22: Verdict | B22: =IF(B18>=0,"Above break-even","Below break-even")
A24: MONTHLY PROFIT: covers per day (down) by ASP (across)
A25: Covers per day / ASP (₹) | B25: 450 | C25: 500 | D25: 550 | E25: 600 | F25: 650
A26: 6 | B26: =$A26*Inputs!$B$7*B$25*Inputs!$B$25-Inputs!$B$18 | C26: =$A26*Inputs!$B$7*C$25*Inputs!$B$25-Inputs!$B$18 | D26: =$A26*Inputs!$B$7*D$25*Inputs!$B$25-Inputs!$B$18 | E26: =$A26*Inputs!$B$7*E$25*Inputs!$B$25-Inputs!$B$18 | F26: =$A26*Inputs!$B$7*F$25*Inputs!$B$25-Inputs!$B$18
A27: 8 | B27: =$A27*Inputs!$B$7*B$25*Inputs!$B$25-Inputs!$B$18 | C27: =$A27*Inputs!$B$7*C$25*Inputs!$B$25-Inputs!$B$18 | D27: =$A27*Inputs!$B$7*D$25*Inputs!$B$25-Inputs!$B$18 | E27: =$A27*Inputs!$B$7*E$25*Inputs!$B$25-Inputs!$B$18 | F27: =$A27*Inputs!$B$7*F$25*Inputs!$B$25-Inputs!$B$18
A28: 10 | B28: =$A28*Inputs!$B$7*B$25*Inputs!$B$25-Inputs!$B$18 | C28: =$A28*Inputs!$B$7*C$25*Inputs!$B$25-Inputs!$B$18 | D28: =$A28*Inputs!$B$7*D$25*Inputs!$B$25-Inputs!$B$18 | E28: =$A28*Inputs!$B$7*E$25*Inputs!$B$25-Inputs!$B$18 | F28: =$A28*Inputs!$B$7*F$25*Inputs!$B$25-Inputs!$B$18
A29: 12 | B29: =$A29*Inputs!$B$7*B$25*Inputs!$B$25-Inputs!$B$18 | C29: =$A29*Inputs!$B$7*C$25*Inputs!$B$25-Inputs!$B$18 | D29: =$A29*Inputs!$B$7*D$25*Inputs!$B$25-Inputs!$B$18 | E29: =$A29*Inputs!$B$7*E$25*Inputs!$B$25-Inputs!$B$18 | F29: =$A29*Inputs!$B$7*F$25*Inputs!$B$25-Inputs!$B$18
A30: 14 | B30: =$A30*Inputs!$B$7*B$25*Inputs!$B$25-Inputs!$B$18 | C30: =$A30*Inputs!$B$7*C$25*Inputs!$B$25-Inputs!$B$18 | D30: =$A30*Inputs!$B$7*D$25*Inputs!$B$25-Inputs!$B$18 | E30: =$A30*Inputs!$B$7*E$25*Inputs!$B$25-Inputs!$B$18 | F30: =$A30*Inputs!$B$7*F$25*Inputs!$B$25-Inputs!$B$18
A31: 16 | B31: =$A31*Inputs!$B$7*B$25*Inputs!$B$25-Inputs!$B$18 | C31: =$A31*Inputs!$B$7*C$25*Inputs!$B$25-Inputs!$B$18 | D31: =$A31*Inputs!$B$7*D$25*Inputs!$B$25-Inputs!$B$18 | E31: =$A31*Inputs!$B$7*E$25*Inputs!$B$25-Inputs!$B$18 | F31: =$A31*Inputs!$B$7*F$25*Inputs!$B$25-Inputs!$B$18
A32: 18 | B32: =$A32*Inputs!$B$7*B$25*Inputs!$B$25-Inputs!$B$18 | C32: =$A32*Inputs!$B$7*C$25*Inputs!$B$25-Inputs!$B$18 | D32: =$A32*Inputs!$B$7*D$25*Inputs!$B$25-Inputs!$B$18 | E32: =$A32*Inputs!$B$7*E$25*Inputs!$B$25-Inputs!$B$18 | F32: =$A32*Inputs!$B$7*F$25*Inputs!$B$25-Inputs!$B$18
A33: 20 | B33: =$A33*Inputs!$B$7*B$25*Inputs!$B$25-Inputs!$B$18 | C33: =$A33*Inputs!$B$7*C$25*Inputs!$B$25-Inputs!$B$18 | D33: =$A33*Inputs!$B$7*D$25*Inputs!$B$25-Inputs!$B$18 | E33: =$A33*Inputs!$B$7*E$25*Inputs!$B$25-Inputs!$B$18 | F33: =$A33*Inputs!$B$7*F$25*Inputs!$B$25-Inputs!$B$18
A34: 22 | B34: =$A34*Inputs!$B$7*B$25*Inputs!$B$25-Inputs!$B$18 | C34: =$A34*Inputs!$B$7*C$25*Inputs!$B$25-Inputs!$B$18 | D34: =$A34*Inputs!$B$7*D$25*Inputs!$B$25-Inputs!$B$18 | E34: =$A34*Inputs!$B$7*E$25*Inputs!$B$25-Inputs!$B$18 | F34: =$A34*Inputs!$B$7*F$25*Inputs!$B$25-Inputs!$B$18
A35: 24 | B35: =$A35*Inputs!$B$7*B$25*Inputs!$B$25-Inputs!$B$18 | C35: =$A35*Inputs!$B$7*C$25*Inputs!$B$25-Inputs!$B$18 | D35: =$A35*Inputs!$B$7*D$25*Inputs!$B$25-Inputs!$B$18 | E35: =$A35*Inputs!$B$7*E$25*Inputs!$B$25-Inputs!$B$18 | F35: =$A35*Inputs!$B$7*F$25*Inputs!$B$25-Inputs!$B$18
A36: 26 | B36: =$A36*Inputs!$B$7*B$25*Inputs!$B$25-Inputs!$B$18 | C36: =$A36*Inputs!$B$7*C$25*Inputs!$B$25-Inputs!$B$18 | D36: =$A36*Inputs!$B$7*D$25*Inputs!$B$25-Inputs!$B$18 | E36: =$A36*Inputs!$B$7*E$25*Inputs!$B$25-Inputs!$B$18 | F36: =$A36*Inputs!$B$7*F$25*Inputs!$B$25-Inputs!$B$18
A37: 28 | B37: =$A37*Inputs!$B$7*B$25*Inputs!$B$25-Inputs!$B$18 | C37: =$A37*Inputs!$B$7*C$25*Inputs!$B$25-Inputs!$B$18 | D37: =$A37*Inputs!$B$7*D$25*Inputs!$B$25-Inputs!$B$18 | E37: =$A37*Inputs!$B$7*E$25*Inputs!$B$25-Inputs!$B$18 | F37: =$A37*Inputs!$B$7*F$25*Inputs!$B$25-Inputs!$B$18
A38: 30 | B38: =$A38*Inputs!$B$7*B$25*Inputs!$B$25-Inputs!$B$18 | C38: =$A38*Inputs!$B$7*C$25*Inputs!$B$25-Inputs!$B$18 | D38: =$A38*Inputs!$B$7*D$25*Inputs!$B$25-Inputs!$B$18 | E38: =$A38*Inputs!$B$7*E$25*Inputs!$B$25-Inputs!$B$18 | F38: =$A38*Inputs!$B$7*F$25*Inputs!$B$25-Inputs!$B$18
A39: Red numbers are monthly losses. Change the blue covers and ASP values to test other cases.

Sheet Seasons
A1: 12-month profit by season
A2: Pick each month's season in column B (Peak, Shoulder, Monsoon). Covers come from Inputs.
A4: Month | B4: Season | C4: Covers/day | D4: Days | E4: Sales | F4: Food cost | G4: Fees & packaging | H4: Fixed costs | I4: Profit | J4: Rent % of sales | K4: Prime cost %
A5: Apr | B5: Shoulder | C5: =INDEX(Inputs!$B$29:$B$31,MATCH(B5,Inputs!$A$29:$A$31,0)) | D5: =Inputs!$B$7 | E5: =C5*D5*Inputs!$B$5 | F5: =E5*Inputs!$B$21 | G5: =E5*Inputs!$B$23 | H5: =Inputs!$B$18 | I5: =E5-F5-G5-H5 | J5: =IFERROR(Inputs!$B$11/E5,0) | K5: =IFERROR((F5+Inputs!$B$12+Inputs!$B$13+Inputs!$B$14)/E5,0)
A6: May | B6: Shoulder | C6: =INDEX(Inputs!$B$29:$B$31,MATCH(B6,Inputs!$A$29:$A$31,0)) | D6: =Inputs!$B$7 | E6: =C6*D6*Inputs!$B$5 | F6: =E6*Inputs!$B$21 | G6: =E6*Inputs!$B$23 | H6: =Inputs!$B$18 | I6: =E6-F6-G6-H6 | J6: =IFERROR(Inputs!$B$11/E6,0) | K6: =IFERROR((F6+Inputs!$B$12+Inputs!$B$13+Inputs!$B$14)/E6,0)
A7: Jun | B7: Monsoon | C7: =INDEX(Inputs!$B$29:$B$31,MATCH(B7,Inputs!$A$29:$A$31,0)) | D7: =Inputs!$B$7 | E7: =C7*D7*Inputs!$B$5 | F7: =E7*Inputs!$B$21 | G7: =E7*Inputs!$B$23 | H7: =Inputs!$B$18 | I7: =E7-F7-G7-H7 | J7: =IFERROR(Inputs!$B$11/E7,0) | K7: =IFERROR((F7+Inputs!$B$12+Inputs!$B$13+Inputs!$B$14)/E7,0)
A8: Jul | B8: Monsoon | C8: =INDEX(Inputs!$B$29:$B$31,MATCH(B8,Inputs!$A$29:$A$31,0)) | D8: =Inputs!$B$7 | E8: =C8*D8*Inputs!$B$5 | F8: =E8*Inputs!$B$21 | G8: =E8*Inputs!$B$23 | H8: =Inputs!$B$18 | I8: =E8-F8-G8-H8 | J8: =IFERROR(Inputs!$B$11/E8,0) | K8: =IFERROR((F8+Inputs!$B$12+Inputs!$B$13+Inputs!$B$14)/E8,0)
A9: Aug | B9: Monsoon | C9: =INDEX(Inputs!$B$29:$B$31,MATCH(B9,Inputs!$A$29:$A$31,0)) | D9: =Inputs!$B$7 | E9: =C9*D9*Inputs!$B$5 | F9: =E9*Inputs!$B$21 | G9: =E9*Inputs!$B$23 | H9: =Inputs!$B$18 | I9: =E9-F9-G9-H9 | J9: =IFERROR(Inputs!$B$11/E9,0) | K9: =IFERROR((F9+Inputs!$B$12+Inputs!$B$13+Inputs!$B$14)/E9,0)
A10: Sep | B10: Shoulder | C10: =INDEX(Inputs!$B$29:$B$31,MATCH(B10,Inputs!$A$29:$A$31,0)) | D10: =Inputs!$B$7 | E10: =C10*D10*Inputs!$B$5 | F10: =E10*Inputs!$B$21 | G10: =E10*Inputs!$B$23 | H10: =Inputs!$B$18 | I10: =E10-F10-G10-H10 | J10: =IFERROR(Inputs!$B$11/E10,0) | K10: =IFERROR((F10+Inputs!$B$12+Inputs!$B$13+Inputs!$B$14)/E10,0)
A11: Oct | B11: Shoulder | C11: =INDEX(Inputs!$B$29:$B$31,MATCH(B11,Inputs!$A$29:$A$31,0)) | D11: =Inputs!$B$7 | E11: =C11*D11*Inputs!$B$5 | F11: =E11*Inputs!$B$21 | G11: =E11*Inputs!$B$23 | H11: =Inputs!$B$18 | I11: =E11-F11-G11-H11 | J11: =IFERROR(Inputs!$B$11/E11,0) | K11: =IFERROR((F11+Inputs!$B$12+Inputs!$B$13+Inputs!$B$14)/E11,0)
A12: Nov | B12: Peak | C12: =INDEX(Inputs!$B$29:$B$31,MATCH(B12,Inputs!$A$29:$A$31,0)) | D12: =Inputs!$B$7 | E12: =C12*D12*Inputs!$B$5 | F12: =E12*Inputs!$B$21 | G12: =E12*Inputs!$B$23 | H12: =Inputs!$B$18 | I12: =E12-F12-G12-H12 | J12: =IFERROR(Inputs!$B$11/E12,0) | K12: =IFERROR((F12+Inputs!$B$12+Inputs!$B$13+Inputs!$B$14)/E12,0)
A13: Dec | B13: Peak | C13: =INDEX(Inputs!$B$29:$B$31,MATCH(B13,Inputs!$A$29:$A$31,0)) | D13: =Inputs!$B$7 | E13: =C13*D13*Inputs!$B$5 | F13: =E13*Inputs!$B$21 | G13: =E13*Inputs!$B$23 | H13: =Inputs!$B$18 | I13: =E13-F13-G13-H13 | J13: =IFERROR(Inputs!$B$11/E13,0) | K13: =IFERROR((F13+Inputs!$B$12+Inputs!$B$13+Inputs!$B$14)/E13,0)
A14: Jan | B14: Peak | C14: =INDEX(Inputs!$B$29:$B$31,MATCH(B14,Inputs!$A$29:$A$31,0)) | D14: =Inputs!$B$7 | E14: =C14*D14*Inputs!$B$5 | F14: =E14*Inputs!$B$21 | G14: =E14*Inputs!$B$23 | H14: =Inputs!$B$18 | I14: =E14-F14-G14-H14 | J14: =IFERROR(Inputs!$B$11/E14,0) | K14: =IFERROR((F14+Inputs!$B$12+Inputs!$B$13+Inputs!$B$14)/E14,0)
A15: Feb | B15: Peak | C15: =INDEX(Inputs!$B$29:$B$31,MATCH(B15,Inputs!$A$29:$A$31,0)) | D15: =Inputs!$B$7 | E15: =C15*D15*Inputs!$B$5 | F15: =E15*Inputs!$B$21 | G15: =E15*Inputs!$B$23 | H15: =Inputs!$B$18 | I15: =E15-F15-G15-H15 | J15: =IFERROR(Inputs!$B$11/E15,0) | K15: =IFERROR((F15+Inputs!$B$12+Inputs!$B$13+Inputs!$B$14)/E15,0)
A16: Mar | B16: Peak | C16: =INDEX(Inputs!$B$29:$B$31,MATCH(B16,Inputs!$A$29:$A$31,0)) | D16: =Inputs!$B$7 | E16: =C16*D16*Inputs!$B$5 | F16: =E16*Inputs!$B$21 | G16: =E16*Inputs!$B$23 | H16: =Inputs!$B$18 | I16: =E16-F16-G16-H16 | J16: =IFERROR(Inputs!$B$11/E16,0) | K16: =IFERROR((F16+Inputs!$B$12+Inputs!$B$13+Inputs!$B$14)/E16,0)
A17: Year total | E17: =SUM(E5:E16) | F17: =SUM(F5:F16) | G17: =SUM(G5:G16) | H17: =SUM(H5:H16) | I17: =SUM(I5:I16)
A19: SUMMARY
A20: Annual sales | B20: =E17
A21: Annual profit before haircut | B21: =I17
A22: Annual profit after safety haircut | B22: =I17*(1-Inputs!B32)
A23: Average monthly profit (after haircut) | B23: =B22/12
A24: Total losses in loss-making months | B24: =SUMIF(I5:I16,"<0")
A25: Number of loss-making months | B25: =COUNTIF(I5:I16,"<0")
A27: Profit is before owner's pay (unless entered on Inputs), income tax, and repair/replacement costs beyond the small allowance.

Sheet Setup
A1: Setup budget and payback
A2: Pulls from Inputs and Seasons.
A3: ONE-TIME COSTS
A4: Rent deposit | B4: =Inputs!B36
A5: Interiors, furniture, lighting | B5: =Inputs!B37
A6: Kitchen equipment | B6: =Inputs!B38
A7: Licences, FSSAI, signage | B7: =Inputs!B39
A8: POS, menu, launch marketing | B8: =Inputs!B40
A9: Crockery, cutlery, opening stock | B9: =Inputs!B41
A10: Setup total | B10: =SUM(B4:B9)
A11: Cash reserve | B11: =Inputs!B42*Inputs!B18 | C11: Months of fixed costs from Inputs.
A12: Total with reserve | B12: =B10+B11
A13: Your budget | B13: =Inputs!B43
A14: Headroom (budget minus total) | B14: =B13-B12 | C14: Negative means the plan exceeds your budget: cut costs or shrink the reserve.
A16: PAYBACK
A17: Setup cost (excluding reserve) | B17: =B10
A18: Average monthly profit (after haircut) | B18: =Seasons!B23
A19: Payback in months (conservative) | B19: =IF(B18>0,B17/B18,"n/a") | C19: Treat any payback under 12 months with suspicion; 18-30 months is normal.
A20: Shoulder-season monthly profit | B20: =INDEX(Seasons!I5:I16,MATCH("Shoulder",Seasons!B5:B16,0))
A21: Payback in months at shoulder profit | B21: =IF(B20>0,B17/B20,"n/a")
A22: Monsoon-type losses over the year | B22: =Seasons!B24
A23: Does the reserve cover those losses? | B23: =IF(B11>=-B22,"Yes","No")

Sheet Menu
A1: Menu pricing check
A2: Dish prices and ingredient costs are my estimates; replace them with your real recipe costs.
A4: Dish | B4: Price (₹, pre-GST) | C4: Ingredient cost (₹) | D4: Share of items sold | E4: Cost incl. waste (₹) | F4: Food cost % (theory) | G4: Food cost % (actual) | H4: Gross margin (₹) | I4: Min price at target (₹) | J4: Status
A5: Steamed momos (6 pc) | B5: 160 | C5: 38 | D5: 0.2 | E5: =C5*(1+Inputs!$B$22) | F5: =IFERROR(C5/B5,0) | G5: =IFERROR(E5/B5,0) | H5: =B5-E5 | I5: =IFERROR(E5/Inputs!$B$21,0) | J5: =IF(G5>Inputs!$B$21,"Above target","OK")
A6: Thukpa | B6: 250 | C6: 68 | D6: 0.1 | E6: =C6*(1+Inputs!$B$22) | F6: =IFERROR(C6/B6,0) | G6: =IFERROR(E6/B6,0) | H6: =B6-E6 | I6: =IFERROR(E6/Inputs!$B$21,0) | J6: =IF(G6>Inputs!$B$21,"Above target","OK")
A7: Veg fried rice / noodles | B7: 230 | C7: 52 | D7: 0.08 | E7: =C7*(1+Inputs!$B$22) | F7: =IFERROR(C7/B7,0) | G7: =IFERROR(E7/B7,0) | H7: =B7-E7 | I7: =IFERROR(E7/Inputs!$B$21,0) | J7: =IF(G7>Inputs!$B$21,"Above target","OK")
A8: Chicken fried rice / noodles | B8: 265 | C8: 72 | D8: 0.12 | E8: =C8*(1+Inputs!$B$22) | F8: =IFERROR(C8/B8,0) | G8: =IFERROR(E8/B8,0) | H8: =B8-E8 | I8: =IFERROR(E8/Inputs!$B$21,0) | J8: =IF(G8>Inputs!$B$21,"Above target","OK")
A9: Chilli chicken | B9: 330 | C9: 92 | D9: 0.14 | E9: =C9*(1+Inputs!$B$22) | F9: =IFERROR(C9/B9,0) | G9: =IFERROR(E9/B9,0) | H9: =B9-E9 | I9: =IFERROR(E9/Inputs!$B$21,0) | J9: =IF(G9>Inputs!$B$21,"Above target","OK")
A10: Kimchi fried rice | B10: 320 | C10: 82 | D10: 0.1 | E10: =C10*(1+Inputs!$B$22) | F10: =IFERROR(C10/B10,0) | G10: =IFERROR(E10/B10,0) | H10: =B10-E10 | I10: =IFERROR(E10/Inputs!$B$21,0) | J10: =IF(G10>Inputs!$B$21,"Above target","OK")
A11: Korean fried chicken wings | B11: 370 | C11: 120 | D11: 0.1 | E11: =C11*(1+Inputs!$B$22) | F11: =IFERROR(C11/B11,0) | G11: =IFERROR(E11/B11,0) | H11: =B11-E11 | I11: =IFERROR(E11/Inputs!$B$21,0) | J11: =IF(G11>Inputs!$B$21,"Above target","OK")
A12: Soft drink / lime / iced tea | B12: 100 | C12: 16 | D12: 0.16 | E12: =C12*(1+Inputs!$B$22) | F12: =IFERROR(C12/B12,0) | G12: =IFERROR(E12/B12,0) | H12: =B12-E12 | I12: =IFERROR(E12/Inputs!$B$21,0) | J12: =IF(G12>Inputs!$B$21,"Above target","OK")
A13: Mix total (must be 100%) | D13: =SUM(D5:D12)
A15: BLENDED RESULT
A16: Weighted average price per item | B16: =SUMPRODUCT(B5:B12,D5:D12)/D13
A17: Weighted ingredient cost incl. waste | B17: =SUMPRODUCT(E5:E12,D5:D12)/D13
A18: Blended food cost % (menu) | B18: =IFERROR(B17/B16,0)
A19: Food cost % assumed in model | B19: =Inputs!B21
A20: Implied ASP (avg price x items per guest) | B20: =B16*Inputs!B9
A21: ASP assumed in model | B21: =Inputs!B5
A22: Check | B22: =IF(ABS(D13-1)>0.001,"Mix % must total 100%",IF(B18>B19+0.02,"Menu runs hotter than the model: raise prices or raise the food cost input","Menu and model roughly agree"))
A24: Min price at target = cost incl. waste divided by the target food cost %. Dishes marked 'Above target' need a price rise, a smaller portion, or a cheaper ingredient.
